{
    "tabs": [
        {
            "label": "face",
            "modelsList": [
                {
                    "title": "Original",
                    "imageName": "https://s3.eu-west-3.amazonaws.com/cnn-art/faceIr.jpg",
                    "trainingResult": "N/A",
                    "testResult": "N/A",
                    "modelImg": "https://s3.eu-west-3.amazonaws.com/cnn-art/noPooling.jpg",
                    "histogram": "https://s3.eu-west-3.amazonaws.com/cnn-art/histograms/face_original_histogram.png"
                    
                },
                {
                    "title": "No pooling layers [128,256,512,256,128,1]",
                    "imageName": "https://s3.eu-west-3.amazonaws.com/cnn-art/noPooling/128,256,512,256,128,1/128,256,512,256,128,1_woback_face.jpg",                        
                    "trainingResult": "https://s3.eu-west-3.amazonaws.com/cnn-art/noPooling/128%2C256%2C512%2C256%2C128%2C1/training_charts/128%2C256%2C512%2C256%2C128%2C1.png",
                    "testResult": "https://s3.eu-west-3.amazonaws.com/cnn-art/noPooling/128,256,512,256,128,1/evaluation_charts/128,256,512,256,128,1_face.png",
                    "modelImg": "https://s3.eu-west-3.amazonaws.com/cnn-art/noPooling/128,256,512,256,128,1/model.jpg",
                    "histogram": "https://s3.eu-west-3.amazonaws.com/cnn-art/noPooling/128,256,512,256,128,1/histograms/histogram_Face.png"
                    
                },
                {
                    "title": "No pooling layers [16,16,16,64,64,64,64,64,64,1]",
                    "imageName": "https://s3.eu-west-3.amazonaws.com/cnn-art/noPooling/16,16,16,64,64,64,64,64,64,1/16,16,16,64,64,64,64,64,64,1_woback_face.jpg",                        
                    "trainingResult": "https://s3.eu-west-3.amazonaws.com/cnn-art/noPooling/16%2C16%2C16%2C64%2C64%2C64%2C64%2C64%2C64%2C1/training_charts/16%2C16%2C16%2C64%2C64%2C64%2C64%2C64%2C64%2C1.png",                
                    "testResult": "https://s3.eu-west-3.amazonaws.com/cnn-art/noPooling/16,16,16,64,64,64,64,64,64,1/evaluation_charts/16,16,16,64,64,64,64,64,64,1_face.png",
                    "modelImg": "https://s3.eu-west-3.amazonaws.com/cnn-art/noPooling/16,16,16,64,64,64,64,64,64,1/model.jpg",
                    "histogram": "https://s3.eu-west-3.amazonaws.com/cnn-art/noPooling/16,16,16,64,64,64,64,64,64,1/histograms/histogram_Face.png"
                    
                },
                {
                    "title": "No pooling layers [16,16,32,32,32,64,64,64,64,1]",
                    "imageName": "https://s3.eu-west-3.amazonaws.com/cnn-art/noPooling/16,16,32,32,32,64,64,64,64,1/16,16,32,32,32,64,64,64,64,1_woback_face.jpg",                        
                    "trainingResult": "https://s3.eu-west-3.amazonaws.com/cnn-art/noPooling/16,16,32,32,32,64,64,64,64,1/training_charts/16,16,32,32,32,64,64,64,64,1.png",                
                    "testResult": "https://s3.eu-west-3.amazonaws.com/cnn-art/noPooling/16,16,32,32,32,64,64,64,64,1/evaluation_charts/16,16,32,32,32,64,64,64,64,1_face.png",
                    "modelImg": "https://s3.eu-west-3.amazonaws.com/cnn-art/noPooling/16,16,32,32,32,64,64,64,64,1/model.jpg",
                    "histogram": "https://s3.eu-west-3.amazonaws.com/cnn-art/noPooling/16,16,16,64,64,64,64,64,64,1/histograms/histogram_Face.png"
                    
                },
                {
                    "title": "No pooling layers [16,16,32,64,128,64,64,32,16,1]",
                    "imageName": "https://s3.eu-west-3.amazonaws.com/cnn-art/noPooling/16,16,32,64,128,64,64,32,16,1/16,16,32,64,128,64,64,32,16,1_woback_face.jpg",                        
                    "trainingResult": "https://s3.eu-west-3.amazonaws.com/cnn-art/noPooling/16,16,32,64,128,64,64,32,16,1/training_charts/16,16,32,64,128,64,64,32,16,1.png",                
                    "testResult": "https://s3.eu-west-3.amazonaws.com/cnn-art/noPooling/16,16,32,64,128,64,64,32,16,1/evaluation_charts/16,16,32,64,128,64,64,32,16,1_face.png",
                    "modelImg": "https://s3.eu-west-3.amazonaws.com/cnn-art/noPooling/16,16,32,64,128,64,64,32,16,1/model.jpg",
                    "histogram": "https://s3.eu-west-3.amazonaws.com/cnn-art/noPooling/16,16,32,64,128,64,64,32,16,1/histograms/histogram_Face.png"
                    
                },
                {
                    "title": "No pooling layers [16,32,64,128,128,128,128,128,128,1]",
                    "imageName": "https://s3.eu-west-3.amazonaws.com/cnn-art/noPooling/16,32,64,128,128,128,128,128,128,1/16,32,64,128,128,128,128,128,128,1_woback_face.jpg",                        
                    "trainingResult": "https://s3.eu-west-3.amazonaws.com/cnn-art/noPooling/16,32,64,128,128,128,128,128,128,1/training_charts/16,32,64,128,128,128,128,128,128,1.png",                
                    "testResult": "https://s3.eu-west-3.amazonaws.com/cnn-art/noPooling/16,32,64,128,128,128,128,128,128,1/evaluation_charts/16,32,64,128,128,128,128,128,128,1_face.png",
                    "modelImg": "https://s3.eu-west-3.amazonaws.com/cnn-art/noPooling/16,32,64,128,128,128,128,128,128,1/model.jpg",
                    "histogram": "https://s3.eu-west-3.amazonaws.com/cnn-art/noPooling/16,32,64,128,128,128,128,128,128,1/histograms/histogram_Face.png"
                    
                },
                {
                    "title": "No pooling layers [16,32,64,128,256,128,64,32,16,1]",
                    "imageName": "https://s3.eu-west-3.amazonaws.com/cnn-art/noPooling/16,32,64,128,256,128,64,32,16,1/16,32,64,128,256,128,64,32,16,1_woback_face.jpg",                        
                    "trainingResult": "https://s3.eu-west-3.amazonaws.com/cnn-art/noPooling/16,32,64,128,256,128,64,32,16,1/training_charts/16,32,64,128,256,128,64,32,16,1.png",                
                    "testResult": "https://s3.eu-west-3.amazonaws.com/cnn-art/noPooling/16,32,64,128,256,128,64,32,16,1/evaluation_charts/16,32,64,128,256,128,64,32,16,1_face.png",
                    "modelImg": "https://s3.eu-west-3.amazonaws.com/cnn-art/noPooling/16,32,64,128,256,128,64,32,16,1/model.jpg",
                    "histogram": "https://s3.eu-west-3.amazonaws.com/cnn-art/noPooling/16,32,64,128,256,128,64,32,16,1/histograms/histogram_Face.png"
                    
                },
                {
                    "title": "No pooling layers [16,32,64,64,64,64,64,32,16,1]",
                    "imageName": "https://s3.eu-west-3.amazonaws.com/cnn-art/noPooling/16,32,64,64,64,64,64,32,16,1/16,32,64,64,64,64,64,32,16,1_woback_face.jpg",                        
                    "trainingResult": "https://s3.eu-west-3.amazonaws.com/cnn-art/noPooling/16,32,64,64,64,64,64,32,16,1/training_charts/16,32,64,64,64,64,64,32,16,1.png",                
                    "testResult": "https://s3.eu-west-3.amazonaws.com/cnn-art/noPooling/16,32,64,64,64,64,64,32,16,1/evaluation_charts/16,32,64,64,64,64,64,32,16,1_face.png",
                    "modelImg": "https://s3.eu-west-3.amazonaws.com/cnn-art/noPooling/16,32,64,64,64,64,64,32,16,1/model.jpg",
                    "histogram": "https://s3.eu-west-3.amazonaws.com/cnn-art/noPooling/16,32,64,64,64,64,64,32,16,1/histograms/histogram_Face.png"
                    
                },
                {
                    "title": "No pooling layers [16,16,32,32,32,64,64,64,64,1]",
                    "imageName": "https://s3.eu-west-3.amazonaws.com/cnn-art/noPooling/16,16,32,32,32,64,64,64,64,1/16,16,32,32,32,64,64,64,64,1_woback_face.jpg",                        
                    "trainingResult": "https://s3.eu-west-3.amazonaws.com/cnn-art/noPooling/16,16,32,32,32,64,64,64,64,1/training_charts/16,16,32,32,32,64,64,64,64,1.png",                
                    "testResult": "https://s3.eu-west-3.amazonaws.com/cnn-art/noPooling/16,16,32,32,32,64,64,64,64,1/evaluation_charts/16,16,32,32,32,64,64,64,64,1_face.png",
                    "modelImg": "https://s3.eu-west-3.amazonaws.com/cnn-art/noPooling/16,16,32,32,32,64,64,64,64,1/model.jpg",
                    "histogram": "https://s3.eu-west-3.amazonaws.com/cnn-art/noPooling/16,16,32,32,32,64,64,64,64,1/histograms/histogram_Face.png"
                    
                },
                {
                    "title": "No pooling layers [16,64,256,64,16,1]",
                    "imageName": "https://s3.eu-west-3.amazonaws.com/cnn-art/noPooling/16,64,256,64,16,1/16,64,256,64,16,1_woback_face.jpg",                        
                    "trainingResult": "https://s3.eu-west-3.amazonaws.com/cnn-art/noPooling/16,64,256,64,16,1/training_charts/16,64,256,64,16,1.png",                
                    "testResult": "https://s3.eu-west-3.amazonaws.com/cnn-art/noPooling/16,64,256,64,16,1/evaluation_charts/16,64,256,64,16,1_face.png",
                    "modelImg": "https://s3.eu-west-3.amazonaws.com/cnn-art/noPooling/16,64,256,64,16,1/model.jpg",
                    "histogram": "https://s3.eu-west-3.amazonaws.com/cnn-art/noPooling/16,64,256,64,16,1/histograms/histogram_Face.png"
                    
                },
                {
                    "title": "No pooling layers [32,64,128,64,32,1]",
                    "imageName": "https://s3.eu-west-3.amazonaws.com/cnn-art/noPooling/32,64,128,64,32,1/32,64,128,64,32,1_woback_face.jpg",                        
                    "trainingResult": "https://s3.eu-west-3.amazonaws.com/cnn-art/noPooling/32,64,128,64,32,1/training_charts/32,64,128,64,32,1.png",                
                    "testResult": "https://s3.eu-west-3.amazonaws.com/cnn-art/noPooling/32,64,128,64,32,1/evaluation_charts/32,64,128,64,32,1_face.png",
                    "modelImg": "https://s3.eu-west-3.amazonaws.com/cnn-art/noPooling/32,64,128,64,32,1/model.jpg",
                    "histogram": "https://s3.eu-west-3.amazonaws.com/cnn-art/noPooling/32%2C64%2C128%2C64%2C32%2C1/histograms/histogram_face.png"
                    
                },
                {
                    "title": "No pooling layers [32,64,64,32,16,32,64,64,32,1]",
                    "imageName": "https://s3.eu-west-3.amazonaws.com/cnn-art/noPooling/32,64,64,32,16,32,64,64,32,1/32,64,64,32,16,32,64,64,32,1_woback_face.jpg",                        
                    "trainingResult": "https://s3.eu-west-3.amazonaws.com/cnn-art/noPooling/32,64,64,32,16,32,64,64,32,1/training_charts/32,64,64,32,16,32,64,64,32,1.png",                
                    "testResult": "https://s3.eu-west-3.amazonaws.com/cnn-art/noPooling/32,64,64,32,16,32,64,64,32,1/evaluation_charts/32,64,64,32,16,32,64,64,32,1_face.png",
                    "modelImg": "https://s3.eu-west-3.amazonaws.com/cnn-art/noPooling/32,64,64,32,16,32,64,64,32,1/model.jpg",
                    "histogram": "https://s3.eu-west-3.amazonaws.com/cnn-art/noPooling/32,64,64,32,16,32,64,64,32,1/histograms/histogram_Face.png"
                    
                },
                {
                    "title": "No pooling layers [4,16,32,64,32,1]",
                    "imageName": "https://s3.eu-west-3.amazonaws.com/cnn-art/noPooling/4,16,32,64,32,1/4,16,32,64,32,1_woback_face.jpg",                        
                    "trainingResult": "https://s3.eu-west-3.amazonaws.com/cnn-art/noPooling/4,16,32,64,32,1/training_charts/4,16,32,64,32,1.png",                
                    "testResult": "https://s3.eu-west-3.amazonaws.com/cnn-art/noPooling/4,16,32,64,32,1/evaluation_charts/4,16,32,64,32,1_face.png",
                    "modelImg": "https://s3.eu-west-3.amazonaws.com/cnn-art/noPooling/4,16,32,64,32,1/model.jpg",
                    "histogram": "https://s3.eu-west-3.amazonaws.com/cnn-art/noPooling/4,16,32,64,32,1/histograms/histogram_Face.png"
                    
                },
                {
                    "title": "No pooling layers [64,64,32,32,16,32,32,64,64,1]",
                    "imageName": "https://s3.eu-west-3.amazonaws.com/cnn-art/noPooling/64,64,32,32,16,32,32,64,64,1/64,64,32,32,16,32,32,64,64,1_woback_face.jpg",                        
                    "trainingResult": "https://s3.eu-west-3.amazonaws.com/cnn-art/noPooling/64,64,32,32,16,32,32,64,64,1/training_charts/64,64,32,32,16,32,32,64,64,1.png",                
                    "testResult": "https://s3.eu-west-3.amazonaws.com/cnn-art/noPooling/64,64,32,32,16,32,32,64,64,1/evaluation_charts/64,64,32,32,16,32,32,64,64,1_face.png",
                    "modelImg": "https://s3.eu-west-3.amazonaws.com/cnn-art/noPooling/64,64,32,32,16,32,32,64,64,1/model.jpg",
                    "histogram": "https://s3.eu-west-3.amazonaws.com/cnn-art/noPooling/64,64,32,32,16,32,32,64,64,1/histograms/histogram_Face.png"
                    
                },
                {
                    "title": "No pooling layers [8,16,16,16,32,32,32,64,32,1]",
                    "imageName": "https://s3.eu-west-3.amazonaws.com/cnn-art/noPooling/8,16,16,16,32,32,32,64,32,1/8,16,16,16,32,32,32,64,32,1_woback_face.jpg",                        
                    "trainingResult": "https://s3.eu-west-3.amazonaws.com/cnn-art/noPooling/8,16,16,16,32,32,32,64,32,1/training_charts/8,16,16,16,32,32,32,64,32,1.png",                
                    "testResult": "https://s3.eu-west-3.amazonaws.com/cnn-art/noPooling/8%2C16%2C16%2C16%2C32%2C32%2C32%2C64%2C32%2C1/evaluation_charts/8%2C16%2C16%2C16%2C32%2C32%2C32%2C64%2C32%2C1_face.png",
                    "modelImg": "https://s3.eu-west-3.amazonaws.com/cnn-art/noPooling/8%2C16%2C16%2C16%2C32%2C32%2C32%2C64%2C32%2C1/model.jpg",
                    "histogram": "https://s3.eu-west-3.amazonaws.com/cnn-art/noPooling/8,16,16,16,32,32,32,64,32,1/histograms/histogram_Face.png"
                    
                },
                {
                    "title": "No pooling layers [8,16,32,64,128,64,32,16,8,1]",
                    "imageName": "https://s3.eu-west-3.amazonaws.com/cnn-art/noPooling/8,16,32,64,128,64,32,16,8,1/8,16,32,64,128,64,32,16,8,1_woback_face.jpg",                        
                    "trainingResult": "https://s3.eu-west-3.amazonaws.com/cnn-art/noPooling/8,16,32,64,128,64,32,16,8,1/training_charts/8,16,32,64,128,64,32,16,8,1.png",                
                    "testResult": "https://s3.eu-west-3.amazonaws.com/cnn-art/noPooling/8,16,32,64,128,64,32,16,8,1/evaluation_charts/8,16,32,64,128,64,32,16,8,1_face.png",
                    "modelImg": "https://s3.eu-west-3.amazonaws.com/cnn-art/noPooling/8,16,32,64,128,64,32,16,8,1/model.jpg",
                    "histogram": "https://s3.eu-west-3.amazonaws.com/cnn-art/noPooling/8,16,32,64,128,64,32,16,8,1/histograms/histogram_Face.png"
                    
                },
                {
                    "title": "No pooling layers [8,32,64,128,32,1]",
                    "imageName": "https://s3.eu-west-3.amazonaws.com/cnn-art/noPooling/8,32,64,128,32,1/8,32,64,128,32,1_woback_face.jpg",                        
                    "trainingResult": "https://s3.eu-west-3.amazonaws.com/cnn-art/noPooling/8,32,64,128,32,1/training_charts/8,32,64,128,32,1.png",                
                    "testResult": "https://s3.eu-west-3.amazonaws.com/cnn-art/noPooling/8,32,64,128,32,1/evaluation_charts/8,32,64,128,32,1_face.png",
                    "modelImg": "https://s3.eu-west-3.amazonaws.com/cnn-art/noPooling/8,32,64,128,32,1/model.jpg",
                    "histogram": "https://s3.eu-west-3.amazonaws.com/cnn-art/noPooling/8,32,64,128,32,1/histograms/histogram_Face.png"
                    
                },
                {
                    "title": "No pooling layers [8,8,16,32,32,32,32,32,32,1]",
                    "imageName": "https://s3.eu-west-3.amazonaws.com/cnn-art/noPooling/8,8,16,32,32,32,32,32,32,1/8,8,16,32,32,32,32,32,32,1_woback_face.jpg",                        
                    "trainingResult": "https://s3.eu-west-3.amazonaws.com/cnn-art/noPooling/8,8,16,32,32,32,32,32,32,1/training_charts/8,8,16,32,32,32,32,32,32,1.png",                
                    "testResult": "https://s3.eu-west-3.amazonaws.com/cnn-art/noPooling/8,8,16,32,32,32,32,32,32,1/evaluation_charts/8,8,16,32,32,32,32,32,32,1_face.png",
                    "modelImg": "https://s3.eu-west-3.amazonaws.com/cnn-art/noPooling/8,8,16,32,32,32,32,32,32,1/model.jpg",
                    "histogram": "https://s3.eu-west-3.amazonaws.com/cnn-art/noPooling/8,8,16,32,32,32,32,32,32,1/histograms/histogram_Face.png"
                    
                }


               
            ]
        },
        {
            "label": "Arch",
            "modelsList":[
                { 
                    "title": "Original Arch",
                    "imageName": "https://s3.eu-west-3.amazonaws.com/cnn-art/arch-IR.jpg",
                    "trainingResult": "N/A",
                    "testResult": "N/A",
                    "modelImg": "https://s3.eu-west-3.amazonaws.com/cnn-art/noPooling.jpg",
                    "histogram": "https://s3.eu-west-3.amazonaws.com/cnn-art/histograms/arch_original.png"
                },
                {
                    "title": "No pooling layers [128,256,512,256,128,1]",
                    "imageName": "https://s3.eu-west-3.amazonaws.com/cnn-art/noPooling/128,256,512,256,128,1/128,256,512,256,128,1_woback_img.jpg",                        
                    "trainingResult": "https://s3.eu-west-3.amazonaws.com/cnn-art/noPooling/128%2C256%2C512%2C256%2C128%2C1/training_charts/128%2C256%2C512%2C256%2C128%2C1.png",
                    "testResult": "https://s3.eu-west-3.amazonaws.com/cnn-art/noPooling/128,256,512,256,128,1/evaluation_charts/128,256,512,256,128,1_img.png",
                    "modelImg": "https://s3.eu-west-3.amazonaws.com/cnn-art/noPooling/128,256,512,256,128,1/model.jpg",
                    "histogram": "https://s3.eu-west-3.amazonaws.com/cnn-art/noPooling/128,256,512,256,128,1/histograms/histogram_Arch.png"
                    
                },
                {
                    "title": "No pooling layers [16,16,16,64,64,64,64,64,64,1]",
                    "imageName": "https://s3.eu-west-3.amazonaws.com/cnn-art/noPooling/16,16,16,64,64,64,64,64,64,1/16,16,16,64,64,64,64,64,64,1_woback_img.jpg",                        
                    "trainingResult": "https://s3.eu-west-3.amazonaws.com/cnn-art/noPooling/16%2C16%2C16%2C64%2C64%2C64%2C64%2C64%2C64%2C1/training_charts/16%2C16%2C16%2C64%2C64%2C64%2C64%2C64%2C64%2C1.png",                
                    "testResult": "https://s3.eu-west-3.amazonaws.com/cnn-art/noPooling/16,16,16,64,64,64,64,64,64,1/evaluation_charts/16,16,16,64,64,64,64,64,64,1_img.png",
                    "modelImg": "https://s3.eu-west-3.amazonaws.com/cnn-art/noPooling/16,16,16,64,64,64,64,64,64,1/model.jpg",
                    "histogram": "https://s3.eu-west-3.amazonaws.com/cnn-art/noPooling/16,16,16,64,64,64,64,64,64,1/histograms/histogram_Arch.png"
                    
                },
                {
                    "title": "No pooling layers [16,16,32,32,32,64,64,64,64,1]",
                    "imageName": "https://s3.eu-west-3.amazonaws.com/cnn-art/noPooling/16,16,16,64,64,64,64,64,64,1/16,16,16,64,64,64,64,64,64,1_woback_img.jpg",                        
                    "trainingResult": "https://s3.eu-west-3.amazonaws.com/cnn-art/noPooling/16,16,16,64,64,64,64,64,64,1/training_charts/16,16,16,64,64,64,64,64,64,1.png",                
                    "testResult": "https://s3.eu-west-3.amazonaws.com/cnn-art/noPooling/16,16,16,64,64,64,64,64,64,1/evaluation_charts/16,16,16,64,64,64,64,64,64,1_img.png",
                    "modelImg": "https://s3.eu-west-3.amazonaws.com/cnn-art/noPooling/16,16,16,64,64,64,64,64,64,1/model.jpg",
                    "histogram": "https://s3.eu-west-3.amazonaws.com/cnn-art/noPooling/16,16,16,64,64,64,64,64,64,1/histograms/histogram_Arch.png"
                    
                },
                {
                    "title": "No pooling layers [16,16,32,64,128,64,64,32,16,1]",
                    "imageName": "https://s3.eu-west-3.amazonaws.com/cnn-art/noPooling/16,16,32,64,128,64,64,32,16,1/16,16,32,64,128,64,64,32,16,1_woback_img.jpg",                        
                    "trainingResult": "https://s3.eu-west-3.amazonaws.com/cnn-art/noPooling/16,16,32,64,128,64,64,32,16,1/training_charts/16,16,32,64,128,64,64,32,16,1.png",                
                    "testResult": "https://s3.eu-west-3.amazonaws.com/cnn-art/noPooling/16,16,32,64,128,64,64,32,16,1/evaluation_charts/16,16,32,64,128,64,64,32,16,1_img.png",
                    "modelImg": "https://s3.eu-west-3.amazonaws.com/cnn-art/noPooling/16,16,32,64,128,64,64,32,16,1/model.jpg",
                    "histogram": "https://s3.eu-west-3.amazonaws.com/cnn-art/noPooling/16,16,32,64,128,64,64,32,16,1/histograms/histogram_Arch.png"
                    
                },
                {
                    "title": "No pooling layers [16,32,64,128,128,128,128,128,128,1]",
                    "imageName": "https://s3.eu-west-3.amazonaws.com/cnn-art/noPooling/16,32,64,128,128,128,128,128,128,1/16,32,64,128,128,128,128,128,128,1_woback_img.jpg",                        
                    "trainingResult": "https://s3.eu-west-3.amazonaws.com/cnn-art/noPooling/16,32,64,128,128,128,128,128,128,1/training_charts/16,32,64,128,128,128,128,128,128,1.png",                
                    "testResult": "https://s3.eu-west-3.amazonaws.com/cnn-art/noPooling/16,32,64,128,128,128,128,128,128,1/evaluation_charts/16,32,64,128,128,128,128,128,128,1_img.png",
                    "modelImg": "https://s3.eu-west-3.amazonaws.com/cnn-art/noPooling/16,32,64,128,128,128,128,128,128,1/model.jpg",
                    "histogram": "https://s3.eu-west-3.amazonaws.com/cnn-art/noPooling/16,32,64,128,128,128,128,128,128,1/histograms/histogram_Arch.png"
                    
                },
                {
                    "title": "No pooling layers [16,32,64,128,256,128,64,32,16,1]",
                    "imageName": "https://s3.eu-west-3.amazonaws.com/cnn-art/noPooling/16,32,64,128,256,128,64,32,16,1/16,32,64,128,256,128,64,32,16,1_woback_img.jpg",                        
                    "trainingResult": "https://s3.eu-west-3.amazonaws.com/cnn-art/noPooling/16,32,64,128,256,128,64,32,16,1/training_charts/16,32,64,128,256,128,64,32,16,1.png",                
                    "testResult": "https://s3.eu-west-3.amazonaws.com/cnn-art/noPooling/16,32,64,128,256,128,64,32,16,1/evaluation_charts/16,32,64,128,256,128,64,32,16,1_img.png",
                    "modelImg": "https://s3.eu-west-3.amazonaws.com/cnn-art/noPooling/16,32,64,128,256,128,64,32,16,1/model.jpg",
                    "histogram": "https://s3.eu-west-3.amazonaws.com/cnn-art/noPooling/16,32,64,128,256,128,64,32,16,1/histograms/histogram_Arch.png"
                    
                },
                {
                    "title": "No pooling layers [16,32,64,64,64,64,64,32,16,1]",
                    "imageName": "https://s3.eu-west-3.amazonaws.com/cnn-art/noPooling/16,32,64,64,64,64,64,32,16,1/16,32,64,64,64,64,64,32,16,1_woback_img.jpg",                        
                    "trainingResult": "https://s3.eu-west-3.amazonaws.com/cnn-art/noPooling/16,32,64,64,64,64,64,32,16,1/training_charts/16,32,64,64,64,64,64,32,16,1.png",                
                    "testResult": "https://s3.eu-west-3.amazonaws.com/cnn-art/noPooling/16,32,64,64,64,64,64,32,16,1/evaluation_charts/16,32,64,64,64,64,64,32,16,1_img.png",
                    "modelImg": "https://s3.eu-west-3.amazonaws.com/cnn-art/noPooling/16,32,64,64,64,64,64,32,16,1/model.jpg",
                    "histogram": "https://s3.eu-west-3.amazonaws.com/cnn-art/noPooling/16,32,64,64,64,64,64,32,16,1/histograms/histogram_Arch.png"
                    
                },
                {
                    "title": "No pooling layers [16,16,32,32,32,64,64,64,64,1]",
                    "imageName": "https://s3.eu-west-3.amazonaws.com/cnn-art/noPooling/16,16,32,32,32,64,64,64,64,1/16,16,32,32,32,64,64,64,64,1_woback_img.jpg",                        
                    "trainingResult": "https://s3.eu-west-3.amazonaws.com/cnn-art/noPooling/16,16,32,32,32,64,64,64,64,1/training_charts/16,16,32,32,32,64,64,64,64,1.png",                
                    "testResult": "https://s3.eu-west-3.amazonaws.com/cnn-art/noPooling/16,16,32,32,32,64,64,64,64,1/evaluation_charts/16,16,32,32,32,64,64,64,64,1_img.png",
                    "modelImg": "https://s3.eu-west-3.amazonaws.com/cnn-art/noPooling/16,16,32,32,32,64,64,64,64,1/model.jpg",
                    "histogram": "https://s3.eu-west-3.amazonaws.com/cnn-art/noPooling/16,16,32,32,32,64,64,64,64,1/histograms/histogram_Arch.png"
                    
                },
                {
                    "title": "No pooling layers [16,64,256,64,16,1]",
                    "imageName": "https://s3.eu-west-3.amazonaws.com/cnn-art/noPooling/16,64,256,64,16,1/16,64,256,64,16,1_woback_img.jpg",                        
                    "trainingResult": "https://s3.eu-west-3.amazonaws.com/cnn-art/noPooling/16,64,256,64,16,1/training_charts/16,64,256,64,16,1.png",                
                    "testResult": "https://s3.eu-west-3.amazonaws.com/cnn-art/noPooling/16,64,256,64,16,1/evaluation_charts/16,64,256,64,16,1_img.png",
                    "modelImg": "https://s3.eu-west-3.amazonaws.com/cnn-art/noPooling/16,64,256,64,16,1/model.jpg",
                    "histogram": "https://s3.eu-west-3.amazonaws.com/cnn-art/noPooling/16,64,256,64,16,1/histograms/histogram_Arch.png"
                    
                },
                {
                    "title": "No pooling layers [32,64,128,64,32,1]",
                    "imageName": "https://s3.eu-west-3.amazonaws.com/cnn-art/noPooling/32,64,128,64,32,1/32,64,128,64,32,1_woback_img.jpg",                        
                    "trainingResult": "https://s3.eu-west-3.amazonaws.com/cnn-art/noPooling/32,64,128,64,32,1/training_charts/32,64,128,64,32,1.png",                
                    "testResult": "https://s3.eu-west-3.amazonaws.com/cnn-art/noPooling/32,64,128,64,32,1/evaluation_charts/32,64,128,64,32,1_img.png",
                    "modelImg": "https://s3.eu-west-3.amazonaws.com/cnn-art/noPooling/32,64,128,64,32,1/model.jpg",
                    "histogram": "https://s3.eu-west-3.amazonaws.com/cnn-art/noPooling/32,64,128,64,32,1/histograms/histogram_Arch.png"
                    
                },
                {
                    "title": "No pooling layers [32,64,64,32,16,32,64,64,32,1]",
                    "imageName": "https://s3.eu-west-3.amazonaws.com/cnn-art/noPooling/32,64,64,32,16,32,64,64,32,1/32,64,64,32,16,32,64,64,32,1_woback_img.jpg",                        
                    "trainingResult": "https://s3.eu-west-3.amazonaws.com/cnn-art/noPooling/32,64,64,32,16,32,64,64,32,1/training_charts/32,64,64,32,16,32,64,64,32,1.png",                
                    "testResult": "https://s3.eu-west-3.amazonaws.com/cnn-art/noPooling/32,64,64,32,16,32,64,64,32,1/evaluation_charts/32,64,64,32,16,32,64,64,32,1_img.png",
                    "modelImg": "https://s3.eu-west-3.amazonaws.com/cnn-art/noPooling/32,64,64,32,16,32,64,64,32,1/model.jpg",
                    "histogram": "https://s3.eu-west-3.amazonaws.com/cnn-art/noPooling/32,64,64,32,16,32,64,64,32,1/histograms/histogram_Arch.png"
                    
                },
                {
                    "title": "No pooling layers [4,16,32,64,32,1]",
                    "imageName": "https://s3.eu-west-3.amazonaws.com/cnn-art/noPooling/4,16,32,64,32,1/4,16,32,64,32,1_woback_img.jpg",                        
                    "trainingResult": "https://s3.eu-west-3.amazonaws.com/cnn-art/noPooling/4,16,32,64,32,1/training_charts/4,16,32,64,32,1.png",                
                    "testResult": "https://s3.eu-west-3.amazonaws.com/cnn-art/noPooling/4,16,32,64,32,1/evaluation_charts/4,16,32,64,32,1_img.png",
                    "modelImg": "https://s3.eu-west-3.amazonaws.com/cnn-art/noPooling/4,16,32,64,32,1/model.jpg",
                    "histogram": "https://s3.eu-west-3.amazonaws.com/cnn-art/noPooling/4,16,32,64,32,1/histograms/histogram_Arch.png"
                    
                },
                {
                    "title": "No pooling layers [64,64,32,32,16,32,32,64,64,1]",
                    "imageName": "https://s3.eu-west-3.amazonaws.com/cnn-art/noPooling/64,64,32,32,16,32,32,64,64,1/64,64,32,32,16,32,32,64,64,1_woback_img.jpg",                        
                    "trainingResult": "https://s3.eu-west-3.amazonaws.com/cnn-art/noPooling/64,64,32,32,16,32,32,64,64,1/training_charts/64,64,32,32,16,32,32,64,64,1.png",                
                    "testResult": "https://s3.eu-west-3.amazonaws.com/cnn-art/noPooling/64,64,32,32,16,32,32,64,64,1/evaluation_charts/64,64,32,32,16,32,32,64,64,1_img.png",
                    "modelImg": "https://s3.eu-west-3.amazonaws.com/cnn-art/noPooling/64,64,32,32,16,32,32,64,64,1/model.jpg",
                    "histogram": "https://s3.eu-west-3.amazonaws.com/cnn-art/noPooling/64,64,32,32,16,32,32,64,64,1/histograms/histogram_Arch.png"
                    
                },
                {
                    "title": "No pooling layers [8,16,16,16,32,32,32,64,32,1]",
                    "imageName": "https://s3.eu-west-3.amazonaws.com/cnn-art/noPooling/8,16,16,16,32,32,32,64,32,1/8,16,16,16,32,32,32,64,32,1_woback_img.jpg",                        
                    "trainingResult": "https://s3.eu-west-3.amazonaws.com/cnn-art/noPooling/8,16,16,16,32,32,32,64,32,1/training_charts/8,16,16,16,32,32,32,64,32,1.png",                
                    "testResult": "https://s3.eu-west-3.amazonaws.com/cnn-art/noPooling/8,16,16,16,32,32,32,64,32,1/evaluation_charts/8,16,16,16,32,32,32,64,32,1   _img.png",
                    "modelImg": "https://s3.eu-west-3.amazonaws.com/cnn-art/noPooling/8,16,16,16,32,32,32,64,32,1/model.jpg",
                    "histogram": "https://s3.eu-west-3.amazonaws.com/cnn-art/noPooling/8,16,16,16,32,32,32,64,32,1/histograms/histogram_Arch.png"
                    
                },
                {
                    "title": "No pooling layers [8,16,32,64,128,64,32,16,8,1]",
                    "imageName": "https://s3.eu-west-3.amazonaws.com/cnn-art/noPooling/8,16,32,64,128,64,32,16,8,1/8,16,32,64,128,64,32,16,8,1_woback_img.jpg",                        
                    "trainingResult": "https://s3.eu-west-3.amazonaws.com/cnn-art/noPooling/8,16,32,64,128,64,32,16,8,1/training_charts/8,16,32,64,128,64,32,16,8,1.png",                
                    "testResult": "https://s3.eu-west-3.amazonaws.com/cnn-art/noPooling/8,16,32,64,128,64,32,16,8,1/evaluation_charts/8,16,32,64,128,64,32,16,8,1_img.png",
                    "modelImg": "https://s3.eu-west-3.amazonaws.com/cnn-art/noPooling/8,16,32,64,128,64,32,16,8,1/model.jpg",
                    "histogram": "https://s3.eu-west-3.amazonaws.com/cnn-art/noPooling/8,16,32,64,128,64,32,16,8,1/histograms/histogram_Arch.png"
                    
                },
                {
                    "title": "No pooling layers [8,32,64,128,32,1]",
                    "imageName": "https://s3.eu-west-3.amazonaws.com/cnn-art/noPooling/8,32,64,128,32,1/8,32,64,128,32,1_woback_img.jpg",                        
                    "trainingResult": "https://s3.eu-west-3.amazonaws.com/cnn-art/noPooling/8,32,64,128,32,1/training_charts/8,32,64,128,32,1.png",                
                    "testResult": "https://s3.eu-west-3.amazonaws.com/cnn-art/noPooling/8,32,64,128,32,1/evaluation_charts/8,32,64,128,32,1_img.png",
                    "modelImg": "https://s3.eu-west-3.amazonaws.com/cnn-art/noPooling/8,32,64,128,32,1/model.jpg",
                    "histogram": "https://s3.eu-west-3.amazonaws.com/cnn-art/noPooling/8,32,64,128,32,1/histograms/histogram_Arch.png"
                    
                },
                {
                    "title": "No pooling layers [8,8,16,32,32,32,32,32,32,1]",
                    "imageName": "https://s3.eu-west-3.amazonaws.com/cnn-art/noPooling/8,8,16,32,32,32,32,32,32,1/8,8,16,32,32,32,32,32,32,1_woback_img.jpg",                        
                    "trainingResult": "https://s3.eu-west-3.amazonaws.com/cnn-art/noPooling/8,8,16,32,32,32,32,32,32,1/training_charts/8,8,16,32,32,32,32,32,32,1.png",                
                    "testResult": "https://s3.eu-west-3.amazonaws.com/cnn-art/noPooling/8,8,16,32,32,32,32,32,32,1/evaluation_charts/8,8,16,32,32,32,32,32,32,1_img.png",
                    "modelImg": "https://s3.eu-west-3.amazonaws.com/cnn-art/noPooling/8,8,16,32,32,32,32,32,32,1/model.jpg",
                    "histogram": "https://s3.eu-west-3.amazonaws.com/cnn-art/noPooling/8,8,16,32,32,32,32,32,32,1/histograms/histogram_Arch.png"
                    
                }
               
              
            ]
        },
        {
            "label": "Robe",
            "modelsList":[
                { 
                    "title": "Robe Original",
                    "imageName": "https://s3.eu-west-3.amazonaws.com/cnn-art/robeIR.jpg",
                    "trainingResult": "N/A",
                    "testResult": "N/A",
                    "modelImg": "https://s3.eu-west-3.amazonaws.com/cnn-art/noPooling.jpg",
                    "histogram": "https://s3.eu-west-3.amazonaws.com/cnn-art/histograms/robe_original.png"
                },
                {
                    "title": "No pooling layers [128,256,512,256,128,1]",
                    "imageName": "https://s3.eu-west-3.amazonaws.com/cnn-art/noPooling/128,256,512,256,128,1/128,256,512,256,128,1_woback_robe.jpg",                        
                    "trainingResult": "https://s3.eu-west-3.amazonaws.com/cnn-art/noPooling/128%2C256%2C512%2C256%2C128%2C1/training_charts/128%2C256%2C512%2C256%2C128%2C1.png",
                    "testResult": "https://s3.eu-west-3.amazonaws.com/cnn-art/noPooling/128,256,512,256,128,1/evaluation_charts/128,256,512,256,128,1_robe.png",
                    "modelImg": "https://s3.eu-west-3.amazonaws.com/cnn-art/noPooling/128,256,512,256,128,1/model.jpg",
                    "histogram": "https://s3.eu-west-3.amazonaws.com/cnn-art/noPooling/128,256,512,256,128,1/histograms/histogram_Robe.png"
                    
                },
                {
                    "title": "No pooling layers [16,16,16,64,64,64,64,64,64,1]",
                    "imageName": "https://s3.eu-west-3.amazonaws.com/cnn-art/noPooling/16,16,16,64,64,64,64,64,64,1/16,16,16,64,64,64,64,64,64,1_woback_robe.jpg",                        
                    "trainingResult": "https://s3.eu-west-3.amazonaws.com/cnn-art/noPooling/16%2C16%2C16%2C64%2C64%2C64%2C64%2C64%2C64%2C1/training_charts/16%2C16%2C16%2C64%2C64%2C64%2C64%2C64%2C64%2C1.png",                
                    "testResult": "https://s3.eu-west-3.amazonaws.com/cnn-art/noPooling/16,16,16,64,64,64,64,64,64,1/evaluation_charts/16,16,16,64,64,64,64,64,64,1_robe.png",
                    "modelImg": "https://s3.eu-west-3.amazonaws.com/cnn-art/noPooling/16,16,16,64,64,64,64,64,64,1/model.jpg",
                    "histogram": "https://s3.eu-west-3.amazonaws.com/cnn-art/noPooling/16,16,16,64,64,64,64,64,64,1/histograms/histogram_Robe.png"
                    
                },
                {
                    "title": "No pooling layers [16,16,32,32,32,64,64,64,64,1]",
                    "imageName": "https://s3.eu-west-3.amazonaws.com/cnn-art/noPooling/16%2C16%2C32%2C32%2C32%2C64%2C64%2C64%2C64%2C1/16%2C16%2C32%2C32%2C32%2C64%2C64%2C64%2C64%2C1_woback_robe.png",                        
                    "trainingResult": "https://s3.eu-west-3.amazonaws.com/cnn-art/noPooling/16%2C16%2C32%2C32%2C32%2C64%2C64%2C64%2C64%2C1/training_charts/16%2C16%2C32%2C32%2C32%2C64%2C64%2C64%2C64%2C1.png",                
                    "testResult": "https://s3.eu-west-3.amazonaws.com/cnn-art/noPooling/16%2C16%2C32%2C32%2C32%2C64%2C64%2C64%2C64%2C1/evaluation_charts/16%2C32%2C64%2C64%2C64%2C64%2C64%2C32%2C16%2C1_robe.png",
                    "modelImg": "https://s3.eu-west-3.amazonaws.com/cnn-art/noPooling/16%2C16%2C32%2C32%2C32%2C64%2C64%2C64%2C64%2C1/model.jpg",
                    "histogram": "https://s3.eu-west-3.amazonaws.com/cnn-art/noPooling/16%2C16%2C32%2C32%2C32%2C64%2C64%2C64%2C64%2C1/histograms/histogram_Robe.png"
                    
                },
                {
                    "title": "No pooling layers [16,16,32,64,128,64,64,32,16,1]",
                    "imageName": "https://s3.eu-west-3.amazonaws.com/cnn-art/noPooling/16%2C16%2C32%2C64%2C128%2C64%2C64%2C32%2C16%2C1/16%2C16%2C32%2C64%2C128%2C64%2C64%2C32%2C16%2C1_woback_robe.jpg",                        
                    "trainingResult": "https://s3.eu-west-3.amazonaws.com/cnn-art/noPooling/16,16,32,64,128,64,64,32,16,1/training_charts/16,16,32,64,128,64,64,32,16,1.png",                
                    "testResult": "https://s3.eu-west-3.amazonaws.com/cnn-art/noPooling/16,16,32,64,128,64,64,32,16,1/evaluation_charts/16,16,32,64,128,64,64,32,16,1_robe.png",
                    "modelImg": "https://s3.eu-west-3.amazonaws.com/cnn-art/noPooling/16,16,32,64,128,64,64,32,16,1/evaluation_charts/model.jpg",
                    "histogram": "https://s3.eu-west-3.amazonaws.com/cnn-art/noPooling/16,16,32,64,128,64,64,32,16,1/histograms/histogram_Robe.png"
                    
                },
                {
                    "title": "No pooling layers [16,32,64,128,128,128,128,128,128,1]",
                    "imageName": "https://s3.eu-west-3.amazonaws.com/cnn-art/noPooling/16%2C32%2C64%2C128%2C128%2C128%2C128%2C128%2C128%2C1/16%2C32%2C64%2C128%2C128%2C128%2C128%2C128%2C128%2C1_woback_robe.jpg",                        
                    "trainingResult": "https://s3.eu-west-3.amazonaws.com/cnn-art/noPooling/16,32,64,128,128,128,128,128,128,1/training_charts/16,32,64,128,128,128,128,128,128,1.png",                
                    "testResult": "https://s3.eu-west-3.amazonaws.com/cnn-art/noPooling/16,32,64,128,128,128,128,128,128,1/evaluation_charts/16,32,64,128,128,128,128,128,128,1_robe.png",
                    "modelImg": "https://s3.eu-west-3.amazonaws.com/cnn-art/noPooling/16,32,64,128,128,128,128,128,128,1/model.jpg",
                    "histogram": "https://s3.eu-west-3.amazonaws.com/cnn-art/noPooling/16,32,64,128,128,128,128,128,128,1/histograms/histogram_Robe.png"
                    
                },
                {
                    "title": "No pooling layers [16,32,64,128,256,128,64,32,16,1]",
                    "imageName": "https://s3.eu-west-3.amazonaws.com/cnn-art/noPooling/16%2C32%2C64%2C64%2C64%2C64%2C64%2C32%2C16%2C1/16%2C32%2C64%2C64%2C64%2C64%2C64%2C32%2C16%2C1_woback_robe.jpg",                        
                    "trainingResult": "https://s3.eu-west-3.amazonaws.com/cnn-art/noPooling/16,32,64,128,256,128,64,32,16,1/training_charts/16,32,64,128,256,128,64,32,16,1.png",                
                    "testResult": "https://s3.eu-west-3.amazonaws.com/cnn-art/noPooling/16,32,64,128,256,128,64,32,16,1/evaluation_charts/16,32,64,128,256,128,64,32,16,1_robe.png",
                    "modelImg": "https://s3.eu-west-3.amazonaws.com/cnn-art/noPooling/16,32,64,128,256,128,64,32,16,1/model.jpg",
                    "histogram": "https://s3.eu-west-3.amazonaws.com/cnn-art/noPooling/16,32,64,128,256,128,64,32,16,1/histograms/histogram_Robe.png"
                    
                },
                {
                    "title": "No pooling layers [16,32,64,64,64,64,64,32,16,1]",
                    "imageName": "https://s3.eu-west-3.amazonaws.com/cnn-art/noPooling/16,32,64,64,64,64,64,32,16,1/16,32,64,64,64,64,64,32,16,1_woback_robe.jpg",                        
                    "trainingResult": "https://s3.eu-west-3.amazonaws.com/cnn-art/noPooling/16,32,64,64,64,64,64,32,16,1/training_charts/16,32,64,64,64,64,64,32,16,1.png",                
                    "testResult": "https://s3.eu-west-3.amazonaws.com/cnn-art/noPooling/16,32,64,64,64,64,64,32,16,1/evaluation_charts/16,32,64,64,64,64,64,32,16,1_robe.png",
                    "modelImg": "https://s3.eu-west-3.amazonaws.com/cnn-art/noPooling/16,32,64,64,64,64,64,32,16,1/model.jpg",
                    "histogram": "https://s3.eu-west-3.amazonaws.com/cnn-art/noPooling/16,32,64,64,64,64,64,32,16,1/histograms/histogram_Robe.png"
                    
                },
                {
                    "title": "No pooling layers 16,64,128,64,16,1]",
                    "imageName": "https://s3.eu-west-3.amazonaws.com/cnn-art/noPooling/16,64,128,64,16,1/16,64,128,64,16,1_woback_robe.jpg",                        
                    "trainingResult": "https://s3.eu-west-3.amazonaws.com/cnn-art/noPooling/16,64,128,64,16,1/training_charts/16,64,128,64,16,1.png",                
                    "testResult": "https://s3.eu-west-3.amazonaws.com/cnn-art/noPooling/16,64,128,64,16,1/evaluation_charts/16,64,128,64,16,1_robe.png",
                    "modelImg": "https://s3.eu-west-3.amazonaws.com/cnn-art/noPooling/16,64,128,64,16,1/model.jpg",
                    "histogram": "https://s3.eu-west-3.amazonaws.com/cnn-art/noPooling/16,64,128,64,16,1/histograms/histogram_Robe.png"
                    
                },
                {
                    "title": "No pooling layers [16,64,256,64,16,1]",
                    "imageName": "https://s3.eu-west-3.amazonaws.com/cnn-art/noPooling/16,64,256,64,16,1/16,64,256,64,16,1_woback_robe.jpg",                        
                    "trainingResult": "https://s3.eu-west-3.amazonaws.com/cnn-art/noPooling/16,64,256,64,16,1/training_charts/16,64,256,64,16,1.png",                
                    "testResult": "https://s3.eu-west-3.amazonaws.com/cnn-art/noPooling/16,64,256,64,16,1/evaluation_charts/16,64,256,64,16,1_robe.png",
                    "modelImg": "https://s3.eu-west-3.amazonaws.com/cnn-art/noPooling/16,64,256,64,16,1/model.jpg",
                    "histogram": "https://s3.eu-west-3.amazonaws.com/cnn-art/noPooling/16,64,256,64,16,1/histograms/histogram_Robe.png"
                    
                },
                {
                    "title": "No pooling layers [32,64,128,64,32,1]",
                    "imageName": "https://s3.eu-west-3.amazonaws.com/cnn-art/noPooling/32,64,128,64,32,1/32,64,128,64,32,1_woback_robe.jpg",                        
                    "trainingResult": "https://s3.eu-west-3.amazonaws.com/cnn-art/noPooling/32,64,128,64,32,1/training_charts/32,64,128,64,32,1.png",                
                    "testResult": "https://s3.eu-west-3.amazonaws.com/cnn-art/noPooling/32,64,128,64,32,1/evaluation_charts/32,64,128,64,32,1_robe.png",
                    "modelImg": "https://s3.eu-west-3.amazonaws.com/cnn-art/noPooling/32,64,128,64,32,1/model.jpg",
                    "histogram": "https://s3.eu-west-3.amazonaws.com/cnn-art/noPooling/32%2C64%2C128%2C64%2C32%2C1/histograms/histogram_robe.png"
                    
                },
                {
                    "title": "No pooling layers [32,64,64,32,16,32,64,64,32,1]",
                    "imageName": "https://s3.eu-west-3.amazonaws.com/cnn-art/noPooling/32,64,64,32,16,32,64,64,32,1/32,64,64,32,16,32,64,64,32,1_woback_robe.jpg",                        
                    "trainingResult": "https://s3.eu-west-3.amazonaws.com/cnn-art/noPooling/32,64,64,32,16,32,64,64,32,1/training_charts/32,64,64,32,16,32,64,64,32,1.png",                
                    "testResult": "https://s3.eu-west-3.amazonaws.com/cnn-art/noPooling/32,64,64,32,16,32,64,64,32,1/evaluation_charts/32,64,64,32,16,32,64,64,32,1_robe.png",
                    "modelImg": "https://s3.eu-west-3.amazonaws.com/cnn-art/noPooling/32,64,64,32,16,32,64,64,32,1/model.jpg",
                    "histogram": "https://s3.eu-west-3.amazonaws.com/cnn-art/noPooling/32,64,64,32,16,32,64,64,32,1/histograms/histogram_Robe.png"
                    
                },
                {
                    "title": "No pooling layers [4,16,32,64,32,1]",
                    "imageName": "https://s3.eu-west-3.amazonaws.com/cnn-art/noPooling/4,16,32,64,32,1/4,16,32,64,32,1_woback_robe.jpg",                        
                    "trainingResult": "https://s3.eu-west-3.amazonaws.com/cnn-art/noPooling/4,16,32,64,32,1/training_charts/4,16,32,64,32,1.png",                
                    "testResult": "https://s3.eu-west-3.amazonaws.com/cnn-art/noPooling/4,16,32,64,32,1/evaluation_charts/4,16,32,64,32,1_robe.png",
                    "modelImg": "https://s3.eu-west-3.amazonaws.com/cnn-art/noPooling/4,16,32,64,32,1/model.jpg",
                    "histogram": "https://s3.eu-west-3.amazonaws.com/cnn-art/noPooling/4,16,32,64,32,1/histograms/histogram_Robe.png"
                    
                },
                {
                    "title": "No pooling layers [64,64,32,32,16,32,32,64,64,1]",
                    "imageName": "https://s3.eu-west-3.amazonaws.com/cnn-art/noPooling/64,64,32,32,16,32,32,64,64,1/64,64,32,32,16,32,32,64,64,1_woback_robe.jpg",                        
                    "trainingResult": "https://s3.eu-west-3.amazonaws.com/cnn-art/noPooling/64,64,32,32,16,32,32,64,64,1/training_charts/64,64,32,32,16,32,32,64,64,1.png",                
                    "testResult": "https://s3.eu-west-3.amazonaws.com/cnn-art/noPooling/64,64,32,32,16,32,32,64,64,1/evaluation_charts/64,64,32,32,16,32,32,64,64,1_robe.png",
                    "modelImg": "https://s3.eu-west-3.amazonaws.com/cnn-art/noPooling/64,64,32,32,16,32,32,64,64,1/model.jpg",
                    "histogram": "https://s3.eu-west-3.amazonaws.com/cnn-art/noPooling/64,64,32,32,16,32,32,64,64,1/histograms/histogram_Robe.png"
                    
                },
                {
                    "title": "No pooling layers [8,16,16,16,32,32,32,64,32,1]",
                    "imageName": "https://s3.eu-west-3.amazonaws.com/cnn-art/noPooling/8,16,16,16,32,32,32,64,32,1/8,16,16,16,32,32,32,64,32,1_woback_robe.jpg",                        
                    "trainingResult": "https://s3.eu-west-3.amazonaws.com/cnn-art/noPooling/8,16,16,16,32,32,32,64,32,1/training_charts/8,16,16,16,32,32,32,64,32,1.png",                
                    "testResult": "https://s3.eu-west-3.amazonaws.com/cnn-art/noPooling/8,16,16,16,32,32,32,64,32,1/evaluation_charts/8,16,16,16,32,32,32,64,32,1_robe.png",
                    "modelImg": "https://s3.eu-west-3.amazonaws.com/cnn-art/noPooling/8,16,16,16,32,32,32,64,32,1/model.jpg",
                    "histogram": "https://s3.eu-west-3.amazonaws.com/cnn-art/noPooling/8,16,16,16,32,32,32,64,32,1/histograms/histogram_Robe.png"
                    
                },
                {
                    "title": "No pooling layers [8,16,32,64,128,64,32,16,8,1]",
                    "imageName": "https://s3.eu-west-3.amazonaws.com/cnn-art/noPooling/8,16,32,64,128,64,32,16,8,1/8,16,32,64,128,64,32,16,8,1_woback_robe.jpg",                        
                    "trainingResult": "https://s3.eu-west-3.amazonaws.com/cnn-art/noPooling/8,16,32,64,128,64,32,16,8,1/training_charts/8,16,32,64,128,64,32,16,8,1.png",                
                    "testResult": "https://s3.eu-west-3.amazonaws.com/cnn-art/noPooling/8,16,32,64,128,64,32,16,8,1/evaluation_charts/8,16,32,64,128,64,32,16,8,1_robe.png",
                    "modelImg": "https://s3.eu-west-3.amazonaws.com/cnn-art/noPooling/8,16,32,64,128,64,32,16,8,1/model.jpg",
                    "histogram": "https://s3.eu-west-3.amazonaws.com/cnn-art/noPooling/8,16,32,64,128,64,32,16,8,1/histograms/histogram_Robe.png"
                    
                },
                {
                    "title": "No pooling layers [8,32,64,128,32,1]",
                    "imageName": "https://s3.eu-west-3.amazonaws.com/cnn-art/noPooling/8,32,64,128,32,1/8,32,64,128,32,1_woback_robe.jpg",                        
                    "trainingResult": "https://s3.eu-west-3.amazonaws.com/cnn-art/noPooling/8,32,64,128,32,1/training_charts/8,32,64,128,32,1.png",                
                    "testResult": "https://s3.eu-west-3.amazonaws.com/cnn-art/noPooling/8,32,64,128,32,1/evaluation_charts/8,32,64,128,32,1_robe.png",
                    "modelImg": "https://s3.eu-west-3.amazonaws.com/cnn-art/noPooling/8,32,64,128,32,1/model.jpg",
                    "histogram": "https://s3.eu-west-3.amazonaws.com/cnn-art/noPooling/8,32,64,128,32,1/histograms/histogram_Robe.png"
                    
                },
                {
                    "title": "No pooling layers [8,8,16,32,32,32,32,32,32,1]",
                    "imageName": "https://s3.eu-west-3.amazonaws.com/cnn-art/noPooling/8,8,16,32,32,32,32,32,32,1/8,8,16,32,32,32,32,32,32,1_woback_robe.jpg",                        
                    "trainingResult": "https://s3.eu-west-3.amazonaws.com/cnn-art/noPooling/8,8,16,32,32,32,32,32,32,1/training_charts/8,8,16,32,32,32,32,32,32,1.png",                
                    "testResult": "https://s3.eu-west-3.amazonaws.com/cnn-art/noPooling/8,8,16,32,32,32,32,32,32,1/evaluation_charts/8,8,16,32,32,32,32,32,32,1_robe.png",
                    "modelImg": "https://s3.eu-west-3.amazonaws.com/cnn-art/noPooling/8,8,16,32,32,32,32,32,32,1/model.jpg",
                    "histogram": "https://s3.eu-west-3.amazonaws.com/cnn-art/noPooling/8,8,16,32,32,32,32,32,32,1/histograms/histogram_Robe.png"
                    
                }
                
            ]
        },
        {
            "label": "Background",
            "modelsList":[
                { 
                    "title": "Original Background",
                    "imageName": "https://s3.eu-west-3.amazonaws.com/cnn-art/IR_background.jpg",
                    "trainingResult": "N/A",
                    "testResult": "N/A",
                    "modelImg": "https://s3.eu-west-3.amazonaws.com/cnn-art/noPooling.jpg",
                    "histogram": "https://s3.eu-west-3.amazonaws.com/cnn-art/histograms/IR_background.png"
                },
                {
                    "title": "No pooling layers [128,256,512,256,128,1]",
                    "imageName": "https://s3.eu-west-3.amazonaws.com/cnn-art/noPooling/128,256,512,256,128,1/128,256,512,256,128,1_woback_background.jpg",                        
                    "trainingResult": "https://s3.eu-west-3.amazonaws.com/cnn-art/noPooling/128%2C256%2C512%2C256%2C128%2C1/training_charts/128%2C256%2C512%2C256%2C128%2C1.png",
                    "testResult": "https://s3.eu-west-3.amazonaws.com/cnn-art/noPooling/128,256,512,256,128,1/evaluation_charts/128,256,512,256,128,1_background.png",
                    "modelImg": "https://s3.eu-west-3.amazonaws.com/cnn-art/noPooling/128,256,512,256,128,1/model.jpg",
                    "histogram": "https://s3.eu-west-3.amazonaws.com/cnn-art/noPooling/128,256,512,256,128,1/histograms/histogram_Background.png"
                    
                },
                {
                    "title": "No pooling layers [16,16,16,64,64,64,64,64,64,1]",
                    "imageName": "https://s3.eu-west-3.amazonaws.com/cnn-art/noPooling/16,16,16,64,64,64,64,64,64,1/16,16,16,64,64,64,64,64,64,1_woback_background.jpg",                        
                    "trainingResult": "https://s3.eu-west-3.amazonaws.com/cnn-art/noPooling/16%2C16%2C16%2C64%2C64%2C64%2C64%2C64%2C64%2C1/training_charts/16%2C16%2C16%2C64%2C64%2C64%2C64%2C64%2C64%2C1.png",                
                    "testResult": "https://s3.eu-west-3.amazonaws.com/cnn-art/noPooling/16,16,16,64,64,64,64,64,64,1/evaluation_charts/16,16,16,64,64,64,64,64,64,1_background.png",
                    "modelImg": "https://s3.eu-west-3.amazonaws.com/cnn-art/noPooling/16,16,16,64,64,64,64,64,64,1/model.jpg",
                    "histogram": "https://s3.eu-west-3.amazonaws.com/cnn-art/noPooling/16,16,16,64,64,64,64,64,64,1/histograms/histogram_Background.png"
                    
                },
                {
                    "title": "No pooling layers [16,16,32,32,32,64,64,64,64,1]",
                    "imageName": "https://s3.eu-west-3.amazonaws.com/cnn-art/noPooling/16,16,32,32,32,64,64,64,64,1/16,16,32,32,32,64,64,64,64,1_woback_background.jpg",                        
                    "trainingResult": "https://s3.eu-west-3.amazonaws.com/cnn-art/noPooling/16,16,32,32,32,64,64,64,64,1/training_charts/16,16,32,32,32,64,64,64,64,1.png",                
                    "testResult": "https://s3.eu-west-3.amazonaws.com/cnn-art/noPooling/16%2C16%2C32%2C32%2C32%2C64%2C64%2C64%2C64%2C1/evaluation_charts/16%2C32%2C64%2C64%2C64%2C64%2C64%2C32%2C16%2C1_background.png",
                    "modelImg": "https://s3.eu-west-3.amazonaws.com/cnn-art/noPooling/16%2C16%2C32%2C32%2C32%2C64%2C64%2C64%2C64%2C1/model.jpg",
                    "histogram": "https://s3.eu-west-3.amazonaws.com/cnn-art/noPooling/16,16,32,32,32,64,64,64,64,1/histograms/histogram_Background.png"
                    
                },
                {
                    "title": "No pooling layers [16,16,32,64,128,64,64,32,16,1]",
                    "imageName": "https://s3.eu-west-3.amazonaws.com/cnn-art/noPooling/16,16,32,64,128,64,64,32,16,1/16,16,32,64,128,64,64,32,16,1_woback_background.jpg",                        
                    "trainingResult": "https://s3.eu-west-3.amazonaws.com/cnn-art/noPooling/16,16,32,64,128,64,64,32,16,1/training_charts/16,16,32,64,128,64,64,32,16,1.png",                
                    "testResult": "https://s3.eu-west-3.amazonaws.com/cnn-art/noPooling/16,16,32,64,128,64,64,32,16,1/evaluation_charts/16,16,32,64,128,64,64,32,16,1_background.png",
                    "modelImg": "https://s3.eu-west-3.amazonaws.com/cnn-art/noPooling/16,16,32,64,128,64,64,32,16,1/model.jpg",
                    "histogram": "https://s3.eu-west-3.amazonaws.com/cnn-art/noPooling/16,16,32,64,128,64,64,32,16,1/histograms/histogram_Background.png"
                    
                },
                {
                    "title": "No pooling layers [16,32,64,128,128,128,128,128,128,1]",
                    "imageName": "https://s3.eu-west-3.amazonaws.com/cnn-art/noPooling/16,32,64,128,128,128,128,128,128,1/16,32,64,128,128,128,128,128,128,1_woback_background.jpg",                        
                    "trainingResult": "https://s3.eu-west-3.amazonaws.com/cnn-art/noPooling/16,32,64,128,128,128,128,128,128,1/training_charts/16,32,64,128,128,128,128,128,128,1.png",                
                    "testResult": "https://s3.eu-west-3.amazonaws.com/cnn-art/noPooling/16,32,64,128,128,128,128,128,128,1/evaluation_charts/16,32,64,128,128,128,128,128,128,1_background.png",
                    "modelImg": "https://s3.eu-west-3.amazonaws.com/cnn-art/noPooling/16,32,64,128,128,128,128,128,128,1/model.jpg",
                    "histogram": "https://s3.eu-west-3.amazonaws.com/cnn-art/noPooling/16,32,64,128,128,128,128,128,128,1/histograms/histogram_Background.png"
                    
                },
                {
                    "title": "No pooling layers [16,32,64,128,256,128,64,32,16,1]",
                    "imageName": "https://s3.eu-west-3.amazonaws.com/cnn-art/noPooling/16,32,64,128,256,128,64,32,16,1/16,32,64,128,256,128,64,32,16,1_woback_background.jpg",                        
                    "trainingResult": "https://s3.eu-west-3.amazonaws.com/cnn-art/noPooling/16,32,64,128,256,128,64,32,16,1/training_charts/16,32,64,128,256,128,64,32,16,1.png",                
                    "testResult": "https://s3.eu-west-3.amazonaws.com/cnn-art/noPooling/16,32,64,128,256,128,64,32,16,1/evaluation_charts/16,32,64,128,256,128,64,32,16,1_background.png",
                    "modelImg": "https://s3.eu-west-3.amazonaws.com/cnn-art/noPooling/16,32,64,128,128,128,128,128,128,1/model.jpg",
                    "histogram": "https://s3.eu-west-3.amazonaws.com/cnn-art/noPooling/16,32,64,128,256,128,64,32,16,1/histograms/histogram_Background.png"
                    
                },
                {
                    "title": "No pooling layers [16,32,64,64,64,64,64,32,16,1]",
                    "imageName": "https://s3.eu-west-3.amazonaws.com/cnn-art/noPooling/16,32,64,64,64,64,64,32,16,1/16,32,64,64,64,64,64,32,16,1_woback_background.jpg",                        
                    "trainingResult": "https://s3.eu-west-3.amazonaws.com/cnn-art/noPooling/16,32,64,64,64,64,64,32,16,1/training_charts/16,32,64,64,64,64,64,32,16,1.png",                
                    "testResult": "https://s3.eu-west-3.amazonaws.com/cnn-art/noPooling/16,32,64,64,64,64,64,32,16,1/evaluation_charts/16,32,64,64,64,64,64,32,16,1_background.png",
                    "modelImg": "https://s3.eu-west-3.amazonaws.com/cnn-art/noPooling/16,32,64,64,64,64,64,32,16,1/model.jpg",
                    "histogram": "https://s3.eu-west-3.amazonaws.com/cnn-art/noPooling/16,32,64,64,64,64,64,32,16,1/histograms/histogram_Background.png"
                    
                },
                {
                    "title": "No pooling layers [16,64,128,64,16,1]",
                    "imageName": "https://s3.eu-west-3.amazonaws.com/cnn-art/noPooling/16,64,128,64,16,1/16,64,128,64,16,1_woback_background.jpg",                        
                    "trainingResult": "https://s3.eu-west-3.amazonaws.com/cnn-art/noPooling/16,64,128,64,16,1/training_charts/16,64,128,64,16,1.png",                
                    "testResult": "https://s3.eu-west-3.amazonaws.com/cnn-art/noPooling/16,64,128,64,16,1/evaluation_charts/16,64,128,64,16,1_background.png",
                    "modelImg": "https://s3.eu-west-3.amazonaws.com/cnn-art/noPooling/16,64,128,64,16,1/model.jpg",
                    "histogram": "https://s3.eu-west-3.amazonaws.com/cnn-art/noPooling/16,64,128,64,16,1/histograms/histogram_Background.png"
                    
                },
                {
                    "title": "No pooling layers [16,64,256,64,16,1]",
                    "imageName": "https://s3.eu-west-3.amazonaws.com/cnn-art/noPooling/16,64,256,64,16,1/16,64,256,64,16,1_woback_background.jpg",                        
                    "trainingResult": "https://s3.eu-west-3.amazonaws.com/cnn-art/noPooling/16,64,256,64,16,1/training_charts/16,64,256,64,16,1.png",                
                    "testResult": "https://s3.eu-west-3.amazonaws.com/cnn-art/noPooling/16,64,256,64,16,1/evaluation_charts/16,64,256,64,16,1_background.png",
                    "modelImg": "pending",
                    "histogram": "https://s3.eu-west-3.amazonaws.com/cnn-art/noPooling/16,64,256,64,16,1/histograms/histogram_Background.png"
                    
                },
                {
                    "title": "No pooling layers [32,64,128,64,32,1]",
                    "imageName": "https://s3.eu-west-3.amazonaws.com/cnn-art/noPooling/32,64,128,64,32,1/32,64,128,64,32,1_woback_background.jpg",                        
                    "trainingResult": "https://s3.eu-west-3.amazonaws.com/cnn-art/noPooling/32,64,128,64,32,1/training_charts/32,64,128,64,32,1.png",                
                    "testResult": "https://s3.eu-west-3.amazonaws.com/cnn-art/noPooling/32,64,128,64,32,1/evaluation_charts/32,64,128,64,32,1_background.png",
                    "modelImg": "pending",
                    "histogram": "https://s3.eu-west-3.amazonaws.com/cnn-art/noPooling/32%2C64%2C128%2C64%2C32%2C1/histograms/histogram_background.png"
                    
                },
                {
                    "title": "No pooling layers [32,64,64,32,16,32,64,64,32,1]",
                    "imageName": "https://s3.eu-west-3.amazonaws.com/cnn-art/noPooling/32,64,64,32,16,32,64,64,32,1/32,64,64,32,16,32,64,64,32,1_woback_background.jpg",                        
                    "trainingResult": "https://s3.eu-west-3.amazonaws.com/cnn-art/noPooling/32,64,64,32,16,32,64,64,32,1/training_charts/32,64,64,32,16,32,64,64,32,1.png",                
                    "testResult": "https://s3.eu-west-3.amazonaws.com/cnn-art/noPooling/32,64,64,32,16,32,64,64,32,1/evaluation_charts/32,64,64,32,16,32,64,64,32,1_background.png",
                    "modelImg": "https://s3.eu-west-3.amazonaws.com/cnn-art/noPooling/32,64,64,32,16,32,64,64,32,1/model.jpg",
                    "histogram": "https://s3.eu-west-3.amazonaws.com/cnn-art/noPooling/32,64,64,32,16,32,64,64,32,1/histograms/histogram_Background.png"
                    
                },
                {
                    "title": "No pooling layers [4,16,32,64,32,1]",
                    "imageName": "https://s3.eu-west-3.amazonaws.com/cnn-art/noPooling/4,16,32,64,32,1/4,16,32,64,32,1_woback_background.jpg",                        
                    "trainingResult": "https://s3.eu-west-3.amazonaws.com/cnn-art/noPooling/4,16,32,64,32,1/training_charts/4,16,32,64,32,1.png",                
                    "testResult": "https://s3.eu-west-3.amazonaws.com/cnn-art/noPooling/4,16,32,64,32,1/evaluation_charts/4,16,32,64,32,1_background.png",
                    "modelImg": "https://s3.eu-west-3.amazonaws.com/cnn-art/noPooling/4,16,32,64,32,1/model.jpg",
                    "histogram": "https://s3.eu-west-3.amazonaws.com/cnn-art/noPooling/4,16,32,64,32,1/histograms/histogram_Background.png"
                    
                },
                {
                    "title": "No pooling layers [64,64,32,32,16,32,32,64,64,1]",
                    "imageName": "https://s3.eu-west-3.amazonaws.com/cnn-art/noPooling/64,64,32,32,16,32,32,64,64,1/64,64,32,32,16,32,32,64,64,1_woback_background.jpg",                        
                    "trainingResult": "https://s3.eu-west-3.amazonaws.com/cnn-art/noPooling/64,64,32,32,16,32,32,64,64,1/training_charts/64,64,32,32,16,32,32,64,64,1.png",                
                    "testResult": "https://s3.eu-west-3.amazonaws.com/cnn-art/noPooling/64,64,32,32,16,32,32,64,64,1/evaluation_charts/64,64,32,32,16,32,32,64,64,1_background.png",
                    "modelImg": "https://s3.eu-west-3.amazonaws.com/cnn-art/noPooling/64,64,32,32,16,32,32,64,64,1/model.jpg",
                    "histogram": "https://s3.eu-west-3.amazonaws.com/cnn-art/noPooling/64,64,32,32,16,32,32,64,64,1/histograms/histogram_Background.png"
                    
                },
                {
                    "title": "No pooling layers [8,16,16,16,32,32,32,64,32,1]",
                    "imageName": "https://s3.eu-west-3.amazonaws.com/cnn-art/noPooling/8,16,16,16,32,32,32,64,32,1/8,16,16,16,32,32,32,64,32,1_woback_background.jpg",                        
                    "trainingResult": "https://s3.eu-west-3.amazonaws.com/cnn-art/noPooling/8,16,16,16,32,32,32,64,32,1/training_charts/8,16,16,16,32,32,32,64,32,1.png",                
                    "testResult": "https://s3.eu-west-3.amazonaws.com/cnn-art/noPooling/8,16,16,16,32,32,32,64,32,1/evaluation_charts/8,16,16,16,32,32,32,64,32,1_background.png",
                    "modelImg": "https://s3.eu-west-3.amazonaws.com/cnn-art/noPooling/64,64,32,32,16,32,32,64,64,1/model.jpg",
                    "histogram": "https://s3.eu-west-3.amazonaws.com/cnn-art/noPooling/8%2C16%2C16%2C16%2C32%2C32%2C32%2C64%2C32%2C1/evaluation_charts/8%2C16%2C16%2C16%2C32%2C32%2C32%2C64%2C32%2C1_background.png"
                    
                },
                {
                    "title": "No pooling layers [8,16,32,64,128,64,32,16,8,1]",
                    "imageName": "https://s3.eu-west-3.amazonaws.com/cnn-art/noPooling/8,16,32,64,128,64,32,16,8,1/8,16,32,64,128,64,32,16,8,1_woback_background.jpg",                        
                    "trainingResult": "https://s3.eu-west-3.amazonaws.com/cnn-art/noPooling/8,16,32,64,128,64,32,16,8,1/training_charts/8,16,32,64,128,64,32,16,8,1.png",                
                    "testResult": "https://s3.eu-west-3.amazonaws.com/cnn-art/noPooling/8,16,32,64,128,64,32,16,8,1/evaluation_charts/8,16,32,64,128,64,32,16,8,1_background.png",
                    "modelImg": "https://s3.eu-west-3.amazonaws.com/cnn-art/noPooling/8,16,32,64,128,64,32,16,8,1/model.jpg",
                    "histogram": "https://s3.eu-west-3.amazonaws.com/cnn-art/noPooling/8,16,32,64,128,64,32,16,8,1/histograms/histogram_Background.png"
                    
                },
                {
                    "title": "No pooling layers [8,32,64,128,32,1]",
                    "imageName": "https://s3.eu-west-3.amazonaws.com/cnn-art/noPooling/8,32,64,128,32,1/8,32,64,128,32,1_woback_background.jpg",                        
                    "trainingResult": "https://s3.eu-west-3.amazonaws.com/cnn-art/noPooling/8,32,64,128,32,1/training_charts/8,32,64,128,32,1.png",                
                    "testResult": "https://s3.eu-west-3.amazonaws.com/cnn-art/noPooling/8,32,64,128,32,1/evaluation_charts/8,32,64,128,32,1_background.png",
                    "modelImg": "https://s3.eu-west-3.amazonaws.com/cnn-art/noPooling/8,32,64,128,32,1/model.jpg",
                    "histogram": "https://s3.eu-west-3.amazonaws.com/cnn-art/noPooling/8,32,64,128,32,1/histograms/histogram_Background.png"
                    
                },
                {
                    "title": "No pooling layers [8,8,16,32,32,32,32,32,32,1]",
                    "imageName": "https://s3.eu-west-3.amazonaws.com/cnn-art/noPooling/8,8,16,32,32,32,32,32,32,1/8,8,16,32,32,32,32,32,32,1_woback_background.jpg",                        
                    "trainingResult": "https://s3.eu-west-3.amazonaws.com/cnn-art/noPooling/8,8,16,32,32,32,32,32,32,1/training_charts/8,8,16,32,32,32,32,32,32,1.png",                
                    "testResult": "https://s3.eu-west-3.amazonaws.com/cnn-art/noPooling/8,8,16,32,32,32,32,32,32,1/evaluation_charts/8,8,16,32,32,32,32,32,32,1_background.png",
                    "modelImg": "https://s3.eu-west-3.amazonaws.com/cnn-art/noPooling/8,8,16,32,32,32,32,32,32,1/model.jpg",
                    "histogram": "https://s3.eu-west-3.amazonaws.com/cnn-art/noPooling/8,8,16,32,32,32,32,32,32,1/histograms/histogram_Background.png"
                    
                }
               
            ]
        }
    ]
}